chcko_r-1.3.2-py3.8-nspkg.pth
chcko/conf.py
chcko/_images/r_dg_c1.png
chcko/_images/r_dg_c2.png
chcko/_images/r_dg_c3.png
chcko/_images/r_dg_c4.png
chcko/_images/r_dg_c5.png
chcko/_images/r_dg_c6.png
chcko/_images/tikz-01804021412cb95dcb40e40d8f0f30a907574188.png
chcko/_images/tikz-0e67550a51cb5cc3f5235164f6ee94e1a2e15b10.png
chcko/_images/tikz-1400ee56889bde311c23a2283ccad7393c769b55.png
chcko/_images/tikz-67ea466ddcc69dee8236e8d23bab2cbff8cd84c2.png
chcko/_images/tikz-d6c3eac40ee7e510d72da06f1d3706f6be24d115.png
chcko/_images/tikz-e9e6f1a445ab137a9fc7bf342a63780e0f23ea18.png
chcko/r/__init__.py
chcko/r/initdb.py
chcko/r/a/__init__.py
chcko/r/a/de.html
chcko/r/a/en.html
chcko/r/a0/__init__.py
chcko/r/a0/_de.html
chcko/r/a0/_en.html
chcko/r/a0/de.rst
chcko/r/a0/en.rst
chcko/r/a1/__init__.py
chcko/r/a1/_de.html
chcko/r/a1/_en.html
chcko/r/a1/de.rst
chcko/r/a1/en.rst
chcko/r/a2/__init__.py
chcko/r/a2/de.html
chcko/r/a2/en.html
chcko/r/a2/x_.html
chcko/r/a3/__init__.py
chcko/r/a3/circuit.html
chcko/r/a3/de.html
chcko/r/a3/en.html
chcko/r/a4/__init__.py
chcko/r/a4/circuit.html
chcko/r/a4/de.html
chcko/r/a4/en.html
chcko/r/a5/__init__.py
chcko/r/a5/_en.html
chcko/r/a5/en.rst
chcko/r/b/__init__.py
chcko/r/b/_de.html
chcko/r/b/_en.html
chcko/r/b/de.rst
chcko/r/b/en.rst
chcko/r/b/vector_dot_cross.tex
chcko/r/ba/__init__.py
chcko/r/ba/de.html
chcko/r/ba/en.html
chcko/r/bb/__init__.py
chcko/r/bb/de.html
chcko/r/bb/en.html
chcko/r/bc/__init__.py
chcko/r/bc/de.html
chcko/r/bc/en.html
chcko/r/bd/__init__.py
chcko/r/bd/de.html
chcko/r/bd/en.html
chcko/r/be/__init__.py
chcko/r/be/de.html
chcko/r/be/en.html
chcko/r/bf/__init__.py
chcko/r/bf/de.html
chcko/r/bf/en.html
chcko/r/bg/__init__.py
chcko/r/bg/de.html
chcko/r/bg/en.html
chcko/r/bh/__init__.py
chcko/r/bh/de.html
chcko/r/bh/en.html
chcko/r/bi/__init__.py
chcko/r/bi/de.html
chcko/r/bi/en.html
chcko/r/bj/__init__.py
chcko/r/bj/de.html
chcko/r/bj/en.html
chcko/r/bk/__init__.py
chcko/r/bk/de.html
chcko/r/bk/en.html
chcko_r-1.3.2.dist-info/METADATA
chcko_r-1.3.2.dist-info/WHEEL
chcko_r-1.3.2.dist-info/namespace_packages.txt
chcko_r-1.3.2.dist-info/top_level.txt
chcko_r-1.3.2.dist-info/RECORD
